{
  "type": "object",
  "properties": {
    "projects": {
      "type": "array",
      "items": {
        "type": "object",
        "properties": {
          "year": {
            "type": "string"
          },
          "title": {
            "type": "string"
          },
          "description": {
            "type": "string"
          },
          "tags": {
            "type": "array",
            "items": {
              "type": "object",
              "properties": {
                "url": {
                  "type": "string",
                  "format": "uri"
                },
                "title": {
                  "type": "string"
                }
              },
              "required": ["url", "title"]
            }
          }
        },
        "required": ["year", "title", "description", "tags"]
      }
    }
  },
  "required": ["projects"]
}
